{
  "sector": "2차전지",
  "etf_code": "305540",
  "date": "20260219",
  "stocks": [
    {
      "code": "006400",
      "name": "삼성SDI",
      "weight": 15.9
    },
    {
      "code": "005490",
      "name": "POSCO홀딩스",
      "weight": 14.27
    },
    {
      "code": "373220",
      "name": "LG에너지솔루션",
      "weight": 12.68
    },
    {
      "code": "051910",
      "name": "LG화학",
      "weight": 11.64
    },
    {
      "code": "086520",
      "name": "에코프로",
      "weight": 9.06
    },
    {
      "code": "003670",
      "name": "포스코퓨처엠",
      "weight": 8.6
    },
    {
      "code": "247540",
      "name": "에코프로비엠",
      "weight": 8.52
    },
    {
      "code": "096770",
      "name": "SK이노베이션",
      "weight": 7.05
    },
    {
      "code": "066970",
      "name": "엘앤에프",
      "weight": 1.97
    },
    {
      "code": "450080",
      "name": "에코프로머티",
      "weight": 1.97
    },
    {
      "code": "011790",
      "name": "SKC",
      "weight": 1.74
    },
    {
      "code": "020150",
      "name": "롯데에너지머티리얼즈",
      "weight": 0.86
    },
    {
      "code": "361610",
      "name": "SK아이이테크놀로지",
      "weight": 0.86
    },
    {
      "code": "348370",
      "name": "엔켐",
      "weight": 0.66
    },
    {
      "code": "005070",
      "name": "코스모신소재",
      "weight": 0.66
    },
    {
      "code": "078600",
      "name": "대주전자재료",
      "weight": 0.52
    },
    {
      "code": "137400",
      "name": "피엔티",
      "weight": 0.47
    },
    {
      "code": "036830",
      "name": "솔브레인홀딩스",
      "weight": 0.4
    },
    {
      "code": "222080",
      "name": "씨아이에스",
      "weight": 0.36
    },
    {
      "code": "093370",
      "name": "후성",
      "weight": 0.33
    },
    {
      "code": "365340",
      "name": "성일하이텍",
      "weight": 0.3
    },
    {
      "code": "005420",
      "name": "코스모화학",
      "weight": 0.25
    },
    {
      "code": "336370",
      "name": "솔루스첨단소재",
      "weight": 0.24
    },
    {
      "code": "278280",
      "name": "천보",
      "weight": 0.23
    },
    {
      "code": "101360",
      "name": "에코앤드림",
      "weight": 0.14
    },
    {
      "code": "393890",
      "name": "더블유씨피",
      "weight": 0.12
    },
    {
      "code": "299030",
      "name": "하나기술",
      "weight": 0.09
    },
    {
      "code": "243840",
      "name": "신흥에스이씨",
      "weight": 0.09
    },
    {
      "code": "010010",
      "name": "Empty DataFrame\nColumns: []\nIndex: []",
      "weight": 0.0
    }
  ]
}